knockoff/__init__.py
knockoff/cli.py
knockoff/cli_v2.py
knockoff/command/__init__.py
knockoff/command/run.py
knockoff/command/version.py
knockoff/exceptions.py
knockoff/factory/__init__.py
knockoff/factory/assembly.py
knockoff/factory/component.py
knockoff/factory/counterfeit.py
knockoff/factory/node.py
knockoff/factory/part.py
knockoff/factory/prototype.py
knockoff/factory/sink.py
knockoff/factory/source.py
knockoff/factory/table.py
knockoff/io.py
knockoff/knockoff.py
knockoff/orm.py
knockoff/sdk/__init__.py
knockoff/sdk/blueprint.py
knockoff/sdk/constraints.py
knockoff/sdk/container/__init__.py
knockoff/sdk/container/default.py
knockoff/sdk/dag.py
knockoff/sdk/db.py
knockoff/sdk/factory/__init__.py
knockoff/sdk/factory/collections.py
knockoff/sdk/factory/column.py
knockoff/sdk/factory/next_strategy/__init__.py
knockoff/sdk/factory/next_strategy/df.py
knockoff/sdk/factory/next_strategy/table.py
knockoff/sdk/table.py
knockoff/tempdb/__init__.py
knockoff/tempdb/container.py
knockoff/tempdb/db.py
knockoff/tempdb/initialize_tables.py
knockoff/tempdb/setup_teardown.py
knockoff/utilities/__init__.py
knockoff/utilities/date/__init__.py
knockoff/utilities/date/interval.py
knockoff/utilities/environ.py
knockoff/utilities/functools.py
knockoff/utilities/importlib_utils.py
knockoff/utilities/io.py
knockoff/utilities/ioc.py
knockoff/utilities/mixin.py
knockoff/utilities/orm/__init__.py
knockoff/utilities/orm/sql.py
knockoff/utilities/orm/sqlalchemy_conn.py
knockoff/utilities/period.py
knockoff/utilities/regex.py
knockoff/utilities/testing/__init__.py
knockoff/utilities/testing/base.py
knockoff/utilities/testing/mysql.py
knockoff/utilities/testing/postgresql.py
knockoff/writer/__init__.py
knockoff/writer/pandas.py
knockoff-4.4.1.dist-info/LICENSE.md
knockoff-4.4.1.dist-info/METADATA
knockoff-4.4.1.dist-info/WHEEL
knockoff-4.4.1.dist-info/entry_points.txt
knockoff-4.4.1.dist-info/RECORD
