Metadata-Version: 2.1
Name: knockoff
Version: 4.4.1
Summary: Library for generating and bootstrapping mock data
Home-page: https://github.com/Nike-Inc/knockoff-factory
License: Apache-2.0
Author: Gregory Yu
Author-email: gregory.yu@nike.com
Maintainer: Mohamed Abdul Huq Ismail
Maintainer-email: Abdul.Ismail@nike.com
Requires-Python: >=3.10.10,<4.0.0
Classifier: License :: OSI Approved :: Apache Software License
Classifier: Programming Language :: Python :: 3
Classifier: Programming Language :: Python :: 3.11
Provides-Extra: complete
Provides-Extra: mysql
Requires-Dist: PyMySQL (>=1.1.0,<1.2.0) ; extra == "mysql" or extra == "complete"
Requires-Dist: PyYaml (>=6.0.1,<7.0.0)
Requires-Dist: Pyrseas (>=0.10.0,<0.11.0) ; extra == "complete"
Requires-Dist: SQLAlchemy (>=2.0.27,<3.0.0)
Requires-Dist: dependency_injector (>=4.41.0,<5.0.0)
Requires-Dist: dotty_dict (>=1.3.1,<2.0.0)
Requires-Dist: faker (>=23.2.1,<24.0.0)
Requires-Dist: joblib (>=1.3.2,<2.0.0)
Requires-Dist: networkx (>=3.2.1,<4.0.0)
Requires-Dist: numpy (>=1.26.4,<2.0.0)
Requires-Dist: pandas (>=2.2.0,<3.0.0)
Requires-Dist: psycopg2 (>=2.9.9,<3.0.0)
Requires-Dist: pyarrow (>=15.0.0,<16.0.0)
Requires-Dist: s3fs (>=2024.2.0,<2025.0.0)
Requires-Dist: sqlalchemy-utils (>=0.41.1,<0.42.0)
Requires-Dist: testing.postgresql (>=1.3.0,<2.0.0)
Project-URL: Repository, https://github.com/Nike-Inc/knockoff-factory
